MANIFEST.in
README.txt
setup.cfg
setup.py
atreal/__init__.py
atreal/__init__.pyc
atreal.portlet.myrecentitems.egg-info/PKG-INFO
atreal.portlet.myrecentitems.egg-info/SOURCES.txt
atreal.portlet.myrecentitems.egg-info/dependency_links.txt
atreal.portlet.myrecentitems.egg-info/entry_points.txt
atreal.portlet.myrecentitems.egg-info/namespace_packages.txt
atreal.portlet.myrecentitems.egg-info/not-zip-safe
atreal.portlet.myrecentitems.egg-info/requires.txt
atreal.portlet.myrecentitems.egg-info/top_level.txt
atreal/portlet/__init__.py
atreal/portlet/__init__.pyc
atreal/portlet/myrecentitems/__init__.py
atreal/portlet/myrecentitems/configure.zcml
atreal/portlet/myrecentitems/myrecentitemsportlet.pt
atreal/portlet/myrecentitems/myrecentitemsportlet.py
atreal/portlet/myrecentitems/locales/atreal.portlet.myrecentitems.pot
atreal/portlet/myrecentitems/locales/fr/LC_MESSAGES/atreal.portlet.myrecentitems.po
atreal/portlet/myrecentitems/profiles/default/metadata.xml
atreal/portlet/myrecentitems/profiles/default/portlets.xml
atreal/portlet/myrecentitems/tests/__init__.py
atreal/portlet/myrecentitems/tests/base.py
atreal/portlet/myrecentitems/tests/test_portlet.py