Metadata-Version: 1.0
Name: atreal.portlet.myrecentitems
Version: 1.0.0
Summary: A recent-like portlet that presents only the user's items
Home-page: http://www.atreal.net
Author: atReal
Author-email: contact@atreal.net
License: GPL
Keywords: plone portlet atreal basic
Platform: UNKNOWN
Classifier: Framework :: Plone
Classifier: Programming Language :: Python
Classifier: Topic :: Software Development :: Libraries :: Python Modules
